package/__init__.py
package/vishwa.py
massdataanalyst-111.111.dist-info/LICENSE
massdataanalyst-111.111.dist-info/METADATA
massdataanalyst-111.111.dist-info/WHEEL
massdataanalyst-111.111.dist-info/top_level.txt
massdataanalyst-111.111.dist-info/RECORD
