Metadata-Version: 2.1
Name: massdataanalyst
Version: 111.111
Summary: A brief description of your project
Author: vishwa
Author-email: vishwa.automationhub@gmail.com
Classifier: Programming Language :: Python :: 3
Classifier: License :: OSI Approved :: MIT License
Classifier: Operating System :: OS Independent
Requires-Python: >=3.6
License-File: LICENSE
